simplyprint_raspberry
